ExploratoryDataAnalysis/EDA.py
ExploratoryDataAnalysis/__init__.py
explore_data-0.0.1.dist-info/LICENSE
explore_data-0.0.1.dist-info/METADATA
explore_data-0.0.1.dist-info/WHEEL
explore_data-0.0.1.dist-info/top_level.txt
explore_data-0.0.1.dist-info/RECORD
