Metadata-Version: 2.1
Name: explore-data
Version: 0.0.1
Summary: A package that performs Exploratory Data Analysis
Home-page: https://github.com/Sumta4real/ExploratoryDataAnalysis
Author: Sumayyah Taiwo
Author-email: sumty4deen@gmail.com
License: MIT
Platform: UNKNOWN
Requires-Dist: numpy
Requires-Dist: pandas
Requires-Dist: matplotlib
Requires-Dist: seaborn
Requires-Dist: scipy
